{
  "project_info": {
    "project_number": "855369189456",
    "project_id": "wakemind-879af",
    "storage_bucket": "wakemind-879af.firebasestorage.app"
  },
  "client": [
    {
      "client_info": {
        "mobilesdk_app_id": "1:855369189456:android:b0ed1b67234a8e8bae6955",
        "android_client_info": {
          "package_name": "com.wgsoftwares.wakemind"
        }
      },
      "oauth_client": [],
      "api_key": [
        {
          "current_key": "AIzaSyAf8_D6NIXESDD2fnADoqcufyJhijjDWlg"
        }
      ],
      "services": {
        "appinvite_service": {
          "other_platform_oauth_client": []
        }
      }
    }
  ],
  "configuration_version": "1"
}